Workbook

Sheet CostOfCollege
B1: Value
A2: College Name | B2: UPenn | D2: Year 1 | E2: Year 2 | F2: Year 3 (at home) | G2: Year 4 (at home)
A3: Cost of college | B3: =AVERAGE(D3:G3) -> 75942 | D3: 83298 | E3: 83298 | F3: 68586 | G3: 68586
A4: Parental Contribution | B4: 40000
A5: Financial Aid | B5: 0
A6: Loan per year | B6: =B3-B4 -> 35942
A7: Loan Rate | B7: =StudentLoanAmortizationSchedule!D4 -> 0.045
A8: Total Loan | B8: =B6*((1 + B7/12)^12+(1 + B7/12)^24+(1 + B7/12)^36+(1 + B7/12)^48 ) -> 161055.82
A10: Highlighted cells require user input to customize

Sheet StudentLoanAmortizationSchedule
B2: Enter Values | F2: Loan Summary | J2: Internals: | K2: This assumes a loan accruing interest during a 4 year period while studying
B3: Loan Amount | D3: =CostOfCollege!B8 -> 161055.82 | F3: Scheduled Payments | H3: =IF($K$3,-PMT(D4/D6,D5*D6,D3),"") -> 1669.1569 | J3: value_entered | K3: =if(D3*D4*D5*D6*D7>0,1,0) -> 1
B4: Annual Interest Rate | D4: 0.045 | F4: Scheduled Number of Payments | H4: =IF(K3,D5*D6,"") -> 120 | J4: header_row | K4: =ROW($10:$10) -> 10
B5: Loan Period in Years | D5: 10 | F5: Actual Number of Payments | H5: =IF(K3,MATCH(0, $I$11:$I$370,0),"") -> 120 | J5: last_row | K5: =if($K$3,K4+H5,K4) -> 130
B6: Number of Payments in Years | D6: 12 | F6: Total Early Payments | H6: =IF(K3,SUMIF($C$11:$C$370,">0",$E$11:$E$370),"") -> 0
B7: Start Date of Loan | D7: 45870 | F7: Total Interest | H7: =IF(K3,SUMIF($C$11:$C$370,">0",$H$11:$H$370),"") -> 39243.007 | J7: 100596.84
B8: Optional Extra Payments | D8: 0
A10: EMI No | B10: Payment Date | C10: Open Balance | D10: Sche. Payments | E10: Extra Payments | F10: Total Payments | G10: Principal | H10: Interest | I10: Close Balance
A11: =if($K$3,1,"") -> 1 | B11: =IFERROR(IF($A$11:$A$370<A11>"",DATE(YEAR($D$7),MONTH($D$7)+$A$11:$A$370*12/$D$6,DAY($D$7)),""),"") -> 45901 | C11: =IF(K3,D3,"") -> 161055.82 | D11: =IF(AND($A$11:$A$370<A11>"",if(A11,1,0)),$H$3,"") -> 1669.1569 | E11: =IF(AND($A$11:$A$370<>"",$D$11:$D$370+$D$8<$C$11:$C$370),$D$8,IF(AND($A$11:$A$370<>"",$C$11:$C$370-$D$11:$D$370>0),$C$11:$C$370-$D$11:$D$370,IF($A$11:$A$370<>"",0,""))) -> 0 | F11: =IF(AND($A$11:$A$370<>"",$D$11:$D$370+$E$11:$E$370<$C$11:$C$370),$D$11:$D$370+$E$11:$E$370,IF($A$11:$A$370<>"",$C$11:$C$370,"")) -> 1669.1569 | G11: =IF($A$11:$A$370<>"",$F$11:$F$370-$H$11:$H$370,"") -> 1065.1976 | H11: =IF($A$11:$A$370<>"",$C$11:$C$370*($D$4/$D$6),"") -> 603.95932 | I11: =IF(AND($A$11:$A$370<>"",$D$11:$D$370+$E$11:$E$370<$C$11:$C$370),$C$11:$C$370-$G$11:$G$370,IF($A$11:$A$370<>"",0,"")) -> 159990.62 | J11: =I11/$D$3 -> 0.99338616
A12: =if(AND($K$3,if(I11,1,0)),A11+1,"") -> 2 | B12: =IF($A$11:$A$370<>"",DATE(YEAR($D$7),MONTH($D$7)+$A$11:$A$370*12/$D$6,DAY($D$7)),"") -> 45931 | C12: =IF($A$11:$A$370<>"",I11,"") -> 159990.62 | D12: =IF(AND($A$11:$A$370<A12>"",if(A12,1,0)),$H$3,"") -> 1669.1569 | E12: =IF(AND($A$11:$A$370<>"",$D$11:$D$370+$D$8<$C$11:$C$370),$D$8,IF(AND($A$11:$A$370<>"",$C$11:$C$370-$D$11:$D$370>0),$C$11:$C$370-$D$11:$D$370,IF($A$11:$A$370<>"",0,""))) -> 0 | F12: =IF(AND($A$11:$A$370<>"",$D$11:$D$370+$E$11:$E$370<$C$11:$C$370),$D$11:$D$370+$E$11:$E$370,IF($A$11:$A$370<>"",$C$11:$C$370,"")) -> 1669.1569 | G12: =IF($A$11:$A$370<>"",$F$11:$F$370-$H$11:$H$370,"") -> 1069.1921 | H12: =IF($A$11:$A$370<>"",$C$11:$C$370*($D$4/$D$6),"") -> 599.96483 | I12: =IF(AND($A$11:$A$370<>"",$D$11:$D$370+$E$11:$E$370<$C$11:$C$370),$C$11:$C$370-$G$11:$G$370,IF($A$11:$A$370<>"",0,"")) -> 158921.43 | J12: =I12/$D$3 -> 0.98674752
A13: =if(AND($K$3,if(I12,1,0)),A12+1,"") -> 3 | B13: =IF($A$11:$A$370<>"",DATE(YEAR($D$7),MONTH($D$7)+$A$11:$A$370*12/$D$6,DAY($D$7)),"") -> 45962 | C13: =IF($A$11:$A$370<>"",I12,"") -> 158921.43 | D13: =IF(AND($A$11:$A$370<A13>"",if(A13,1,0)),$H$3,"") -> 1669.1569 | E13: =IF(AND($A$11:$A$370<>"",$D$11:$D$370+$D$8<$C$11:$C$370),$D$8,IF(AND($A$11:$A$370<>"",$C$11:$C$370-$D$11:$D$370>0),$C$11:$C$370-$D$11:$D$370,IF($A$11:$A$370<>"",0,""))) -> 0 | F13: =IF(AND($A$11:$A$370<>"",$D$11:$D$370+$E$11:$E$370<$C$11:$C$370),$D$11:$D$370+$E$11:$E$370,IF($A$11:$A$370<>"",$C$11:$C$370,"")) -> 1669.1569 | G13: =IF($A$11:$A$370<>"",$F$11:$F$370-$H$11:$H$370,"") -> 1073.2015 | H13: =IF($A$11:$A$370<>"",$C$11:$C$370*($D$4/$D$6),"") -> 595.95536 | I13: =IF(AND($A$11:$A$370<>"",$D$11:$D$370+$E$11:$E$370<$C$11:$C$370),$C$11:$C$370-$G$11:$G$370,IF($A$11:$A$370<>"",0,"")) -> 157848.23 | J13: =I13/$D$3 -> 0.98008398
A14: =if(AND($K$3,if(I13,1,0)),A13+1,"") -> 4 | B14: =IF($A$11:$A$370<>"",DATE(YEAR($D$7),MONTH($D$7)+$A$11:$A$370*12/$D$6,DAY($D$7)),"") -> 45992 | C14: =IF($A$11:$A$370<>"",I13,"") -> 157848.23 | D14: =IF(AND($A$11:$A$370<A14>"",if(A14,1,0)),$H$3,"") -> 1669.1569 | E14: =IF(AND($A$11:$A$370<>"",$D$11:$D$370+$D$8<$C$11:$C$370),$D$8,IF(AND($A$11:$A$370<>"",$C$11:$C$370-$D$11:$D$370>0),$C$11:$C$370-$D$11:$D$370,IF($A$11:$A$370<>"",0,""))) -> 0 | F14: =IF(AND($A$11:$A$370<>"",$D$11:$D$370+$E$11:$E$370<$C$11:$C$370),$D$11:$D$370+$E$11:$E$370,IF($A$11:$A$370<>"",$C$11:$C$370,"")) -> 1669.1569 | G14: =IF($A$11:$A$370<>"",$F$11:$F$370-$H$11:$H$370,"") -> 1077.226 | H14: =IF($A$11:$A$370<>"",$C$11:$C$370*($D$4/$D$6),"") -> 591.93086 | I14: =IF(AND($A$11:$A$370<>"",$D$11:$D$370+$E$11:$E$370<$C$11:$C$370),$C$11:$C$370-$G$11:$G$370,IF($A$11:$A$370<>"",0,"")) -> 156771 | J14: =I14/$D$3 -> 0.97339545
A15: =if(AND($K$3,if(I14,1,0)),A14+1,"") -> 5 | B15: =IF($A$11:$A$370<>"",DATE(YEAR($D$7),MONTH($D$7)+$A$11:$A$370*12/$D$6,DAY($D$7)),"") -> 46023 | C15: =IF($A$11:$A$370<>"",I14,"") -> 156771 | D15: =IF(AND($A$11:$A$370<A15>"",if(A15,1,0)),$H$3,"") -> 1669.1569 | E15: =IF(AND($A$11:$A$370<>"",$D$11:$D$370+$D$8<$C$11:$C$370),$D$8,IF(AND($A$11:$A$370<>"",$C$11:$C$370-$D$11:$D$370>0),$C$11:$C$370-$D$11:$D$370,IF($A$11:$A$370<>"",0,""))) -> 0 | F15: =IF(AND($A$11:$A$370<>"",$D$11:$D$370+$E$11:$E$370<$C$11:$C$370),$D$11:$D$370+$E$11:$E$370,IF($A$11:$A$370<>"",$C$11:$C$370,"")) -> 1669.1569 | G15: =IF($A$11:$A$370<>"",$F$11:$F$370-$H$11:$H$370,"") -> 1081.2656 | H15: =IF($A$11:$A$370<>"",$C$11:$C$370*($D$4/$D$6),"") -> 587.89126 | I15: =IF(AND($A$11:$A$370<>"",$D$11:$D$370+$E$11:$E$370<$C$11:$C$370),$C$11:$C$370-$G$11:$G$370,IF($A$11:$A$370<>"",0,"")) -> 155689.74 | J15: =I15/$D$3 -> 0.96668184
A16: =if(AND($K$3,if(I15,1,0)),A15+1,"") -> 6 | B16: =IF($A$11:$A$370<>"",DATE(YEAR($D$7),MONTH($D$7)+$A$11:$A$370*12/$D$6,DAY($D$7)),"") -> 46054 | C16: =IF($A$11:$A$370<>"",I15,"") -> 155689.74 | D16: =IF(AND($A$11:$A$370<A16>"",if(A16,1,0)),$H$3,"") -> 1669.1569 | E16: =IF(AND($A$11:$A$370<>"",$D$11:$D$370+$D$8<$C$11:$C$370),$D$8,IF(AND($A$11:$A$370<>"",$C$11:$C$370-$D$11:$D$370>0),$C$11:$C$370-$D$11:$D$370,IF($A$11:$A$370<>"",0,""))) -> 0 | F16: =IF(AND($A$11:$A$370<>"",$D$11:$D$370+$E$11:$E$370<$C$11:$C$370),$D$11:$D$370+$E$11:$E$370,IF($A$11:$A$370<>"",$C$11:$C$370,"")) -> 1669.1569 | G16: =IF($A$11:$A$370<>"",$F$11:$F$370-$H$11:$H$370,"") -> 1085.3204 | H16: =IF($A$11:$A$370<>"",$C$11:$C$370*($D$4/$D$6),"") -> 583.83651 | I16: =IF(AND($A$11:$A$370<>"",$D$11:$D$370+$E$11:$E$370<$C$11:$C$370),$C$11:$C$370-$G$11:$G$370,IF($A$11:$A$370<>"",0,"")) -> 154604.42 | J16: =I16/$D$3 -> 0.95994306
A17: =if(AND($K$3,if(I16,1,0)),A16+1,"") -> 7 | B17: =IF($A$11:$A$370<>"",DATE(YEAR($D$7),MONTH($D$7)+$A$11:$A$370*12/$D$6,DAY($D$7)),"") -> 46082 | C17: =IF($A$11:$A$370<>"",I16,"") -> 154604.42 | D17: =IF(AND($A$11:$A$370<A17>"",if(A17,1,0)),$H$3,"") -> 1669.1569 | E17: =IF(AND($A$11:$A$370<>"",$D$11:$D$370+$D$8<$C$11:$C$370),$D$8,IF(AND($A$11:$A$370<>"",$C$11:$C$370-$D$11:$D$370>0),$C$11:$C$370-$D$11:$D$370,IF($A$11:$A$370<>"",0,""))) -> 0 | F17: =IF(AND($A$11:$A$370<>"",$D$11:$D$370+$E$11:$E$370<$C$11:$C$370),$D$11:$D$370+$E$11:$E$370,IF($A$11:$A$370<>"",$C$11:$C$370,"")) -> 1669.1569 | G17: =IF($A$11:$A$370<>"",$F$11:$F$370-$H$11:$H$370,"") -> 1089.3903 | H17: =IF($A$11:$A$370<>"",$C$11:$C$370*($D$4/$D$6),"") -> 579.76656 | I17: =IF(AND($A$11:$A$370<>"",$D$11:$D$370+$E$11:$E$370<$C$11:$C$370),$C$11:$C$370-$G$11:$G$370,IF($A$11:$A$370<>"",0,"")) -> 153515.03 | J17: =I17/$D$3 -> 0.95317901
A18: =if(AND($K$3,if(I17,1,0)),A17+1,"") -> 8 | B18: =IF($A$11:$A$370<>"",DATE(YEAR($D$7),MONTH($D$7)+$A$11:$A$370*12/$D$6,DAY($D$7)),"") -> 46113 | C18: =IF($A$11:$A$370<>"",I17,"") -> 153515.03 | D18: =IF(AND($A$11:$A$370<A18>"",if(A18,1,0)),$H$3,"") -> 1669.1569 | E18: =IF(AND($A$11:$A$370<>"",$D$11:$D$370+$D$8<$C$11:$C$370),$D$8,IF(AND($A$11:$A$370<>"",$C$11:$C$370-$D$11:$D$370>0),$C$11:$C$370-$D$11:$D$370,IF($A$11:$A$370<>"",0,""))) -> 0 | F18: =IF(AND($A$11:$A$370<>"",$D$11:$D$370+$E$11:$E$370<$C$11:$C$370),$D$11:$D$370+$E$11:$E$370,IF($A$11:$A$370<>"",$C$11:$C$370,"")) -> 1669.1569 | G18: =IF($A$11:$A$370<>"",$F$11:$F$370-$H$11:$H$370,"") -> 1093.4755 | H18: =IF($A$11:$A$370<>"",$C$11:$C$370*($D$4/$D$6),"") -> 575.68135 | I18: =IF(AND($A$11:$A$370<>"",$D$11:$D$370+$E$11:$E$370<$C$11:$C$370),$C$11:$C$370-$G$11:$G$370,IF($A$11:$A$370<>"",0,"")) -> 152421.55 | J18: =I18/$D$3 -> 0.94638959
A19: =if(AND($K$3,if(I18,1,0)),A18+1,"") -> 9 | B19: =IF($A$11:$A$370<>"",DATE(YEAR($D$7),MONTH($D$7)+$A$11:$A$370*12/$D$6,DAY($D$7)),"") -> 46143 | C19: =IF($A$11:$A$370<>"",I18,"") -> 152421.55 | D19: =IF(AND($A$11:$A$370<A19>"",if(A19,1,0)),$H$3,"") -> 1669.1569 | E19: =IF(AND($A$11:$A$370<>"",$D$11:$D$370+$D$8<$C$11:$C$370),$D$8,IF(AND($A$11:$A$370<>"",$C$11:$C$370-$D$11:$D$370>0),$C$11:$C$370-$D$11:$D$370,IF($A$11:$A$370<>"",0,""))) -> 0 | F19: =IF(AND($A$11:$A$370<>"",$D$11:$D$370+$E$11:$E$370<$C$11:$C$370),$D$11:$D$370+$E$11:$E$370,IF($A$11:$A$370<>"",$C$11:$C$370,"")) -> 1669.1569 | G19: =IF($A$11:$A$370<>"",$F$11:$F$370-$H$11:$H$370,"") -> 1097.5761 | H19: =IF($A$11:$A$370<>"",$C$11:$C$370*($D$4/$D$6),"") -> 571.58082 | I19: =IF(AND($A$11:$A$370<>"",$D$11:$D$370+$E$11:$E$370<$C$11:$C$370),$C$11:$C$370-$G$11:$G$370,IF($A$11:$A$370<>"",0,"")) -> 151323.97 | J19: =I19/$D$3 -> 0.93957471
A20: =if(AND($K$3,if(I19,1,0)),A19+1,"") -> 10 | B20: =IF($A$11:$A$370<>"",DATE(YEAR($D$7),MONTH($D$7)+$A$11:$A$370*12/$D$6,DAY($D$7)),"") -> 46174 | C20: =IF($A$11:$A$370<>"",I19,"") -> 151323.97 | D20: =IF(AND($A$11:$A$370<A20>"",if(A20,1,0)),$H$3,"") -> 1669.1569 | E20: =IF(AND($A$11:$A$370<>"",$D$11:$D$370+$D$8<$C$11:$C$370),$D$8,IF(AND($A$11:$A$370<>"",$C$11:$C$370-$D$11:$D$370>0),$C$11:$C$370-$D$11:$D$370,IF($A$11:$A$370<>"",0,""))) -> 0 | F20: =IF(AND($A$11:$A$370<>"",$D$11:$D$370+$E$11:$E$370<$C$11:$C$370),$D$11:$D$370+$E$11:$E$370,IF($A$11:$A$370<>"",$C$11:$C$370,"")) -> 1669.1569 | G20: =IF($A$11:$A$370<>"",$F$11:$F$370-$H$11:$H$370,"") -> 1101.692 | H20: =IF($A$11:$A$370<>"",$C$11:$C$370*($D$4/$D$6),"") -> 567.46491 | I20: =IF(AND($A$11:$A$370<>"",$D$11:$D$370+$E$11:$E$370<$C$11:$C$370),$C$11:$C$370-$G$11:$G$370,IF($A$11:$A$370<>"",0,"")) -> 150222.28 | J20: =I20/$D$3 -> 0.93273427
A21: =if(AND($K$3,if(I20,1,0)),A20+1,"") -> 11 | B21: =IF($A$11:$A$370<>"",DATE(YEAR($D$7),MONTH($D$7)+$A$11:$A$370*12/$D$6,DAY($D$7)),"") -> 46204 | C21: =IF($A$11:$A$370<>"",I20,"") -> 150222.28 | D21: =IF(AND($A$11:$A$370<A21>"",if(A21,1,0)),$H$3,"") -> 1669.1569 | E21: =IF(AND($A$11:$A$370<>"",$D$11:$D$370+$D$8<$C$11:$C$370),$D$8,IF(AND($A$11:$A$370<>"",$C$11:$C$370-$D$11:$D$370>0),$C$11:$C$370-$D$11:$D$370,IF($A$11:$A$370<>"",0,""))) -> 0 | F21: =IF(AND($A$11:$A$370<>"",$D$11:$D$370+$E$11:$E$370<$C$11:$C$370),$D$11:$D$370+$E$11:$E$370,IF($A$11:$A$370<>"",$C$11:$C$370,"")) -> 1669.1569 | G21: =IF($A$11:$A$370<>"",$F$11:$F$370-$H$11:$H$370,"") -> 1105.8233 | H21: =IF($A$11:$A$370<>"",$C$11:$C$370*($D$4/$D$6),"") -> 563.33356 | I21: =IF(AND($A$11:$A$370<>"",$D$11:$D$370+$E$11:$E$370<$C$11:$C$370),$C$11:$C$370-$G$11:$G$370,IF($A$11:$A$370<>"",0,"")) -> 149116.46 | J21: =I21/$D$3 -> 0.92586818
A22: =if(AND($K$3,if(I21,1,0)),A21+1,"") -> 12 | B22: =IF($A$11:$A$370<>"",DATE(YEAR($D$7),MONTH($D$7)+$A$11:$A$370*12/$D$6,DAY($D$7)),"") -> 46235 | C22: =IF($A$11:$A$370<>"",I21,"") -> 149116.46 | D22: =IF(AND($A$11:$A$370<A22>"",if(A22,1,0)),$H$3,"") -> 1669.1569 | E22: =IF(AND($A$11:$A$370<>"",$D$11:$D$370+$D$8<$C$11:$C$370),$D$8,IF(AND($A$11:$A$370<>"",$C$11:$C$370-$D$11:$D$370>0),$C$11:$C$370-$D$11:$D$370,IF($A$11:$A$370<>"",0,""))) -> 0 | F22: =IF(AND($A$11:$A$370<>"",$D$11:$D$370+$E$11:$E$370<$C$11:$C$370),$D$11:$D$370+$E$11:$E$370,IF($A$11:$A$370<>"",$C$11:$C$370,"")) -> 1669.1569 | G22: =IF($A$11:$A$370<>"",$F$11:$F$370-$H$11:$H$370,"") -> 1109.9702 | H22: =IF($A$11:$A$370<>"",$C$11:$C$370*($D$4/$D$6),"") -> 559.18672 | I22: =IF(AND($A$11:$A$370<>"",$D$11:$D$370+$E$11:$E$370<$C$11:$C$370),$C$11:$C$370-$G$11:$G$370,IF($A$11:$A$370<>"",0,"")) -> 148006.49 | J22: =I22/$D$3 -> 0.91897635
A23: =if(AND($K$3,if(I22,1,0)),A22+1,"") -> 13 | B23: =IF($A$11:$A$370<>"",DATE(YEAR($D$7),MONTH($D$7)+$A$11:$A$370*12/$D$6,DAY($D$7)),"") -> 46266 | C23: =IF($A$11:$A$370<>"",I22,"") -> 148006.49 | D23: =IF(AND($A$11:$A$370<A23>"",if(A23,1,0)),$H$3,"") -> 1669.1569 | E23: =IF(AND($A$11:$A$370<>"",$D$11:$D$370+$D$8<$C$11:$C$370),$D$8,IF(AND($A$11:$A$370<>"",$C$11:$C$370-$D$11:$D$370>0),$C$11:$C$370-$D$11:$D$370,IF($A$11:$A$370<>"",0,""))) -> 0 | F23: =IF(AND($A$11:$A$370<>"",$D$11:$D$370+$E$11:$E$370<$C$11:$C$370),$D$11:$D$370+$E$11:$E$370,IF($A$11:$A$370<>"",$C$11:$C$370,"")) -> 1669.1569 | G23: =IF($A$11:$A$370<>"",$F$11:$F$370-$H$11:$H$370,"") -> 1114.1326 | H23: =IF($A$11:$A$370<>"",$C$11:$C$370*($D$4/$D$6),"") -> 555.02433 | I23: =IF(AND($A$11:$A$370<>"",$D$11:$D$370+$E$11:$E$370<$C$11:$C$370),$C$11:$C$370-$G$11:$G$370,IF($A$11:$A$370<>"",0,"")) -> 146892.36 | J23: =I23/$D$3 -> 0.91205867
... A130: =if(AND($K$3,if(I129,1,0)),A129+1,"") -> 120 | B130: =IF($A$11:$A$370<>"",DATE(YEAR($D$7),MONTH($D$7)+$A$11:$A$370*12/$D$6,DAY($D$7)),"") -> 49522 | C130: =IF($A$11:$A$370<>"",I129,"") -> 1662.9209 | D130: =IF(AND($A$11:$A$370<A130>"",if(A130,1,0)),$H$3,"") -> 1669.1569 | E130: =IF(AND($A$11:$A$370<>"",$D$11:$D$370+$D$8<$C$11:$C$370),$D$8,IF(AND($A$11:$A$370<>"",$C$11:$C$370-$D$11:$D$370>0),$C$11:$C$370-$D$11:$D$370,IF($A$11:$A$370<>"",0,""))) -> 0 | F130: =IF(AND($A$11:$A$370<>"",$D$11:$D$370+$E$11:$E$370<$C$11:$C$370),$D$11:$D$370+$E$11:$E$370,IF($A$11:$A$370<>"",$C$11:$C$370,"")) -> 1662.9209 | G130: =IF($A$11:$A$370<>"",$F$11:$F$370-$H$11:$H$370,"") -> 1656.685 | H130: =IF($A$11:$A$370<>"",$C$11:$C$370*($D$4/$D$6),"") -> 6.2359535 | I130: =IF(AND($A$11:$A$370<>"",$D$11:$D$370+$E$11:$E$370<$C$11:$C$370),$C$11:$C$370-$G$11:$G$370,IF($A$11:$A$370<>"",0,"")) -> 0 | J130: =I130/$D$3 -> 0
A131: =if(AND($K$3,if(I130,1,0)),A130+1,"") | B131: =IF($A$11:$A$370<>"",DATE(YEAR($D$7),MONTH($D$7)+$A$11:$A$370*12/$D$6,DAY($D$7)),"") | C131: =IF($A$11:$A$370<>"",I130,"") | D131: =IF(AND($A$11:$A$370<A131>"",if(A131,1,0)),$H$3,"") | E131: =IF(AND($A$11:$A$370<>"",$D$11:$D$370+$D$8<$C$11:$C$370),$D$8,IF(AND($A$11:$A$370<>"",$C$11:$C$370-$D$11:$D$370>0),$C$11:$C$370-$D$11:$D$370,IF($A$11:$A$370<>"",0,""))) | F131: =IF(AND($A$11:$A$370<>"",$D$11:$D$370+$E$11:$E$370<$C$11:$C$370),$D$11:$D$370+$E$11:$E$370,IF($A$11:$A$370<>"",$C$11:$C$370,"")) | G131: =IF($A$11:$A$370<>"",$F$11:$F$370-$H$11:$H$370,"") | H131: =IF($A$11:$A$370<>"",$C$11:$C$370*($D$4/$D$6),"") | I131: =IF(AND($A$11:$A$370<>"",$D$11:$D$370+$E$11:$E$370<$C$11:$C$370),$C$11:$C$370-$G$11:$G$370,IF($A$11:$A$370<>"",0,""))
A132: =if(AND($K$3,if(I131,1,0)),A131+1,"") | B132: =IF($A$11:$A$370<>"",DATE(YEAR($D$7),MONTH($D$7)+$A$11:$A$370*12/$D$6,DAY($D$7)),"") | C132: =IF($A$11:$A$370<>"",I131,"") | D132: =IF(AND($A$11:$A$370<A132>"",if(A132,1,0)),$H$3,"") | E132: =IF(AND($A$11:$A$370<>"",$D$11:$D$370+$D$8<$C$11:$C$370),$D$8,IF(AND($A$11:$A$370<>"",$C$11:$C$370-$D$11:$D$370>0),$C$11:$C$370-$D$11:$D$370,IF($A$11:$A$370<>"",0,""))) | F132: =IF(AND($A$11:$A$370<>"",$D$11:$D$370+$E$11:$E$370<$C$11:$C$370),$D$11:$D$370+$E$11:$E$370,IF($A$11:$A$370<>"",$C$11:$C$370,"")) | G132: =IF($A$11:$A$370<>"",$F$11:$F$370-$H$11:$H$370,"") | H132: =IF($A$11:$A$370<>"",$C$11:$C$370*($D$4/$D$6),"") | I132: =IF(AND($A$11:$A$370<>"",$D$11:$D$370+$E$11:$E$370<$C$11:$C$370),$C$11:$C$370-$G$11:$G$370,IF($A$11:$A$370<>"",0,""))
A133: =if(AND($K$3,if(I132,1,0)),A132+1,"") | B133: =IF($A$11:$A$370<>"",DATE(YEAR($D$7),MONTH($D$7)+$A$11:$A$370*12/$D$6,DAY($D$7)),"") | C133: =IF($A$11:$A$370<>"",I132,"") | D133: =IF(AND($A$11:$A$370<A133>"",if(A133,1,0)),$H$3,"") | E133: =IF(AND($A$11:$A$370<>"",$D$11:$D$370+$D$8<$C$11:$C$370),$D$8,IF(AND($A$11:$A$370<>"",$C$11:$C$370-$D$11:$D$370>0),$C$11:$C$370-$D$11:$D$370,IF($A$11:$A$370<>"",0,""))) | F133: =IF(AND($A$11:$A$370<>"",$D$11:$D$370+$E$11:$E$370<$C$11:$C$370),$D$11:$D$370+$E$11:$E$370,IF($A$11:$A$370<>"",$C$11:$C$370,"")) | G133: =IF($A$11:$A$370<>"",$F$11:$F$370-$H$11:$H$370,"") | H133: =IF($A$11:$A$370<>"",$C$11:$C$370*($D$4/$D$6),"") | I133: =IF(AND($A$11:$A$370<>"",$D$11:$D$370+$E$11:$E$370<$C$11:$C$370),$C$11:$C$370-$G$11:$G$370,IF($A$11:$A$370<>"",0,""))
A134: =if(AND($K$3,if(I133,1,0)),A133+1,"") | B134: =IF($A$11:$A$370<>"",DATE(YEAR($D$7),MONTH($D$7)+$A$11:$A$370*12/$D$6,DAY($D$7)),"") | C134: =IF($A$11:$A$370<>"",I133,"") | D134: =IF(AND($A$11:$A$370<A134>"",if(A134,1,0)),$H$3,"") | E134: =IF(AND($A$11:$A$370<>"",$D$11:$D$370+$D$8<$C$11:$C$370),$D$8,IF(AND($A$11:$A$370<>"",$C$11:$C$370-$D$11:$D$370>0),$C$11:$C$370-$D$11:$D$370,IF($A$11:$A$370<>"",0,""))) | F134: =IF(AND($A$11:$A$370<>"",$D$11:$D$370+$E$11:$E$370<$C$11:$C$370),$D$11:$D$370+$E$11:$E$370,IF($A$11:$A$370<>"",$C$11:$C$370,"")) | G134: =IF($A$11:$A$370<>"",$F$11:$F$370-$H$11:$H$370,"") | H134: =IF($A$11:$A$370<>"",$C$11:$C$370*($D$4/$D$6),"") | I134: =IF(AND($A$11:$A$370<>"",$D$11:$D$370+$E$11:$E$370<$C$11:$C$370),$C$11:$C$370-$G$11:$G$370,IF($A$11:$A$370<>"",0,""))
A135: =if(AND($K$3,if(I134,1,0)),A134+1,"") | B135: =IF($A$11:$A$370<>"",DATE(YEAR($D$7),MONTH($D$7)+$A$11:$A$370*12/$D$6,DAY($D$7)),"") | C135: =IF($A$11:$A$370<>"",I134,"") | D135: =IF(AND($A$11:$A$370<A135>"",if(A135,1,0)),$H$3,"") | E135: =IF(AND($A$11:$A$370<>"",$D$11:$D$370+$D$8<$C$11:$C$370),$D$8,IF(AND($A$11:$A$370<>"",$C$11:$C$370-$D$11:$D$370>0),$C$11:$C$370-$D$11:$D$370,IF($A$11:$A$370<>"",0,""))) | F135: =IF(AND($A$11:$A$370<>"",$D$11:$D$370+$E$11:$E$370<$C$11:$C$370),$D$11:$D$370+$E$11:$E$370,IF($A$11:$A$370<>"",$C$11:$C$370,"")) | G135: =IF($A$11:$A$370<>"",$F$11:$F$370-$H$11:$H$370,"") | H135: =IF($A$11:$A$370<>"",$C$11:$C$370*($D$4/$D$6),"") | I135: =IF(AND($A$11:$A$370<>"",$D$11:$D$370+$E$11:$E$370<$C$11:$C$370),$C$11:$C$370-$G$11:$G$370,IF($A$11:$A$370<>"",0,""))
A136: =if(AND($K$3,if(I135,1,0)),A135+1,"") | B136: =IF($A$11:$A$370<>"",DATE(YEAR($D$7),MONTH($D$7)+$A$11:$A$370*12/$D$6,DAY($D$7)),"") | C136: =IF($A$11:$A$370<>"",I135,"") | D136: =IF(AND($A$11:$A$370<A136>"",if(A136,1,0)),$H$3,"") | E136: =IF(AND($A$11:$A$370<>"",$D$11:$D$370+$D$8<$C$11:$C$370),$D$8,IF(AND($A$11:$A$370<>"",$C$11:$C$370-$D$11:$D$370>0),$C$11:$C$370-$D$11:$D$370,IF($A$11:$A$370<>"",0,""))) | F136: =IF(AND($A$11:$A$370<>"",$D$11:$D$370+$E$11:$E$370<$C$11:$C$370),$D$11:$D$370+$E$11:$E$370,IF($A$11:$A$370<>"",$C$11:$C$370,"")) | G136: =IF($A$11:$A$370<>"",$F$11:$F$370-$H$11:$H$370,"") | H136: =IF($A$11:$A$370<>"",$C$11:$C$370*($D$4/$D$6),"") | I136: =IF(AND($A$11:$A$370<>"",$D$11:$D$370+$E$11:$E$370<$C$11:$C$370),$C$11:$C$370-$G$11:$G$370,IF($A$11:$A$370<>"",0,""))
A137: =if(AND($K$3,if(I136,1,0)),A136+1,"") | B137: =IF($A$11:$A$370<>"",DATE(YEAR($D$7),MONTH($D$7)+$A$11:$A$370*12/$D$6,DAY($D$7)),"") | C137: =IF($A$11:$A$370<>"",I136,"") | D137: =IF(AND($A$11:$A$370<A137>"",if(A137,1,0)),$H$3,"") | E137: =IF(AND($A$11:$A$370<>"",$D$11:$D$370+$D$8<$C$11:$C$370),$D$8,IF(AND($A$11:$A$370<>"",$C$11:$C$370-$D$11:$D$370>0),$C$11:$C$370-$D$11:$D$370,IF($A$11:$A$370<>"",0,""))) | F137: =IF(AND($A$11:$A$370<>"",$D$11:$D$370+$E$11:$E$370<$C$11:$C$370),$D$11:$D$370+$E$11:$E$370,IF($A$11:$A$370<>"",$C$11:$C$370,"")) | G137: =IF($A$11:$A$370<>"",$F$11:$F$370-$H$11:$H$370,"") | H137: =IF($A$11:$A$370<>"",$C$11:$C$370*($D$4/$D$6),"") | I137: =IF(AND($A$11:$A$370<>"",$D$11:$D$370+$E$11:$E$370<$C$11:$C$370),$C$11:$C$370-$G$11:$G$370,IF($A$11:$A$370<>"",0,""))
A138: =if(AND($K$3,if(I137,1,0)),A137+1,"") | B138: =IF($A$11:$A$370<>"",DATE(YEAR($D$7),MONTH($D$7)+$A$11:$A$370*12/$D$6,DAY($D$7)),"") | C138: =IF($A$11:$A$370<>"",I137,"") | D138: =IF(AND($A$11:$A$370<A138>"",if(A138,1,0)),$H$3,"") | E138: =IF(AND($A$11:$A$370<>"",$D$11:$D$370+$D$8<$C$11:$C$370),$D$8,IF(AND($A$11:$A$370<>"",$C$11:$C$370-$D$11:$D$370>0),$C$11:$C$370-$D$11:$D$370,IF($A$11:$A$370<>"",0,""))) | F138: =IF(AND($A$11:$A$370<>"",$D$11:$D$370+$E$11:$E$370<$C$11:$C$370),$D$11:$D$370+$E$11:$E$370,IF($A$11:$A$370<>"",$C$11:$C$370,"")) | G138: =IF($A$11:$A$370<>"",$F$11:$F$370-$H$11:$H$370,"") | H138: =IF($A$11:$A$370<>"",$C$11:$C$370*($D$4/$D$6),"") | I138: =IF(AND($A$11:$A$370<>"",$D$11:$D$370+$E$11:$E$370<$C$11:$C$370),$C$11:$C$370-$G$11:$G$370,IF($A$11:$A$370<>"",0,""))
A139: =if(AND($K$3,if(I138,1,0)),A138+1,"") | B139: =IF($A$11:$A$370<>"",DATE(YEAR($D$7),MONTH($D$7)+$A$11:$A$370*12/$D$6,DAY($D$7)),"") | C139: =IF($A$11:$A$370<>"",I138,"") | D139: =IF(AND($A$11:$A$370<A139>"",if(A139,1,0)),$H$3,"") | E139: =IF(AND($A$11:$A$370<>"",$D$11:$D$370+$D$8<$C$11:$C$370),$D$8,IF(AND($A$11:$A$370<>"",$C$11:$C$370-$D$11:$D$370>0),$C$11:$C$370-$D$11:$D$370,IF($A$11:$A$370<>"",0,""))) | F139: =IF(AND($A$11:$A$370<>"",$D$11:$D$370+$E$11:$E$370<$C$11:$C$370),$D$11:$D$370+$E$11:$E$370,IF($A$11:$A$370<>"",$C$11:$C$370,"")) | G139: =IF($A$11:$A$370<>"",$F$11:$F$370-$H$11:$H$370,"") | H139: =IF($A$11:$A$370<>"",$C$11:$C$370*($D$4/$D$6),"") | I139: =IF(AND($A$11:$A$370<>"",$D$11:$D$370+$E$11:$E$370<$C$11:$C$370),$C$11:$C$370-$G$11:$G$370,IF($A$11:$A$370<>"",0,""))
A140: =if(AND($K$3,if(I139,1,0)),A139+1,"") | B140: =IF($A$11:$A$370<>"",DATE(YEAR($D$7),MONTH($D$7)+$A$11:$A$370*12/$D$6,DAY($D$7)),"") | C140: =IF($A$11:$A$370<>"",I139,"") | D140: =IF(AND($A$11:$A$370<A140>"",if(A140,1,0)),$H$3,"") | E140: =IF(AND($A$11:$A$370<>"",$D$11:$D$370+$D$8<$C$11:$C$370),$D$8,IF(AND($A$11:$A$370<>"",$C$11:$C$370-$D$11:$D$370>0),$C$11:$C$370-$D$11:$D$370,IF($A$11:$A$370<>"",0,""))) | F140: =IF(AND($A$11:$A$370<>"",$D$11:$D$370+$E$11:$E$370<$C$11:$C$370),$D$11:$D$370+$E$11:$E$370,IF($A$11:$A$370<>"",$C$11:$C$370,"")) | G140: =IF($A$11:$A$370<>"",$F$11:$F$370-$H$11:$H$370,"") | H140: =IF($A$11:$A$370<>"",$C$11:$C$370*($D$4/$D$6),"") | I140: =IF(AND($A$11:$A$370<>"",$D$11:$D$370+$E$11:$E$370<$C$11:$C$370),$C$11:$C$370-$G$11:$G$370,IF($A$11:$A$370<>"",0,""))
A141: =if(AND($K$3,if(I140,1,0)),A140+1,"") | B141: =IF($A$11:$A$370<>"",DATE(YEAR($D$7),MONTH($D$7)+$A$11:$A$370*12/$D$6,DAY($D$7)),"") | C141: =IF($A$11:$A$370<>"",I140,"") | D141: =IF(AND($A$11:$A$370<A141>"",if(A141,1,0)),$H$3,"") | E141: =IF(AND($A$11:$A$370<>"",$D$11:$D$370+$D$8<$C$11:$C$370),$D$8,IF(AND($A$11:$A$370<>"",$C$11:$C$370-$D$11:$D$370>0),$C$11:$C$370-$D$11:$D$370,IF($A$11:$A$370<>"",0,""))) | F141: =IF(AND($A$11:$A$370<>"",$D$11:$D$370+$E$11:$E$370<$C$11:$C$370),$D$11:$D$370+$E$11:$E$370,IF($A$11:$A$370<>"",$C$11:$C$370,"")) | G141: =IF($A$11:$A$370<>"",$F$11:$F$370-$H$11:$H$370,"") | H141: =IF($A$11:$A$370<>"",$C$11:$C$370*($D$4/$D$6),"") | I141: =IF(AND($A$11:$A$370<>"",$D$11:$D$370+$E$11:$E$370<$C$11:$C$370),$C$11:$C$370-$G$11:$G$370,IF($A$11:$A$370<>"",0,""))
A142: =if(AND($K$3,if(I141,1,0)),A141+1,"") | B142: =IF($A$11:$A$370<>"",DATE(YEAR($D$7),MONTH($D$7)+$A$11:$A$370*12/$D$6,DAY($D$7)),"") | C142: =IF($A$11:$A$370<>"",I141,"") | D142: =IF(AND($A$11:$A$370<A142>"",if(A142,1,0)),$H$3,"") | E142: =IF(AND($A$11:$A$370<>"",$D$11:$D$370+$D$8<$C$11:$C$370),$D$8,IF(AND($A$11:$A$370<>"",$C$11:$C$370-$D$11:$D$370>0),$C$11:$C$370-$D$11:$D$370,IF($A$11:$A$370<>"",0,""))) | F142: =IF(AND($A$11:$A$370<>"",$D$11:$D$370+$E$11:$E$370<$C$11:$C$370),$D$11:$D$370+$E$11:$E$370,IF($A$11:$A$370<>"",$C$11:$C$370,"")) | G142: =IF($A$11:$A$370<>"",$F$11:$F$370-$H$11:$H$370,"") | H142: =IF($A$11:$A$370<>"",$C$11:$C$370*($D$4/$D$6),"") | I142: =IF(AND($A$11:$A$370<>"",$D$11:$D$370+$E$11:$E$370<$C$11:$C$370),$C$11:$C$370-$G$11:$G$370,IF($A$11:$A$370<>"",0,""))
... A370: =if(AND($K$3,if(I369,1,0)),A369+1,"") | B370: =IF($A$11:$A$370<>"",DATE(YEAR($D$7),MONTH($D$7)+$A$11:$A$370*12/$D$6,DAY($D$7)),"") | C370: =IF($A$11:$A$370<>"",I369,"") | D370: =IF(AND($A$11:$A$370<A370>"",if(A370,1,0)),$H$3,"") | E370: =IF(AND($A$11:$A$370<>"",$D$11:$D$370+$D$8<$C$11:$C$370),$D$8,IF(AND($A$11:$A$370<>"",$C$11:$C$370-$D$11:$D$370>0),$C$11:$C$370-$D$11:$D$370,IF($A$11:$A$370<>"",0,""))) | F370: =IF(AND($A$11:$A$370<>"",$D$11:$D$370+$E$11:$E$370<$C$11:$C$370),$D$11:$D$370+$E$11:$E$370,IF($A$11:$A$370<>"",$C$11:$C$370,"")) | G370: =IF($A$11:$A$370<>"",$F$11:$F$370-$H$11:$H$370,"") | H370: =IF($A$11:$A$370<>"",$C$11:$C$370*($D$4/$D$6),"") | I370: =IF(AND($A$11:$A$370<>"",$D$11:$D$370+$E$11:$E$370<$C$11:$C$370),$C$11:$C$370-$G$11:$G$370,IF($A$11:$A$370<>"",0,""))

Sheet Income+MonthlyExpenses
B2: Value | C2: Tax | D2: Rate | F2: UPenn Salaries | G2: https://www.vpul.upenn.edu/careerservices/files/2017_Senior_Survey_FINAL_PDF.pdf
A3: Annual Income | B3: 107500 | F3: PennState | G3: https://www.collegesimply.com/colleges/pennsylvania/pennsylvania-state-university-main-campus/salaries/
A4: Federal Taxes | B4: ='Tax Calculator'!B4 -> 15294 | F4: GeorgiaTech | G4: https://www.collegesimply.com/colleges/georgia/georgia-institute-of-technology-main-campus/salaries/
A5: State Taxes | B5: =B3*D5 -> 6450 | C5: State Tax Rate | D5: 0.06
A6: Medicare | B6: =B3*D6 -> 1558.75 | C6: Medicare Rate | D6: 0.0145
A7: Social Security | B7: =B3*D7 -> 6665 | C7: Social Security Rate | D7: 0.062
A8: City/County Taxes | B8: =B3*D8 -> 0 | C8: City Taxes | D8: 0
A9: Monthly Leftovers | B9: =(B3-(Sum(B4:B8)))/12 -> 6461.0208
A12: Rent | B12: 1200
A13: Groceries & Eating Out | B13: 400
A14: Utilities (includes phone, internet) | B14: 250
A15: Transportation | B15: 200
A16: HealthCare | B16: 150
A17: Miscellaneous | B17: 300 | E17: 401k Max for 2021
A18: CollegeLoan | B18: =StudentLoanAmortizationSchedule!H3 -> 1669.1569 | E18: 19500
A19: Car Insurance | B19: 200 | E19: 401K Max | F19: 401K planned
A20: 401K contribution (Optional) | B20: =MIN(E20:F20) -> 1625 | C20: Total Savings Over 10 yrs | E20: =E18/12 -> 1625 | F20: 2500
A21: LEFTOVERS from Leftovers (Savings) | B21: =B9-SUM(B12:B20) -> 466.86394 | C21: =B21*12*StudentLoanAmortizationSchedule!D5 -> 56023.673
A23: Highlighted cells require user input to customize

Sheet Tax Calculator
A1: Enter Filing Type | B1: Single
A2: Enter Taxable Income | B2: ='Income+MonthlyExpenses'!B3-('Income+MonthlyExpenses'!B20*12) -> 88000
A4: Estimated Federal Tax | B4: =if(B1="Single", max(H12:H17), max(H22:H27)) -> 15294
A5: Marginal Tax Rate | B5: {=index(F12:F27, match(B4,H12:H27, 0))} -> 0.24
A6: Average Tax Rate | B6: =B4/B2 -> 0.17379545
A9: Schedules - UPDATED FOR 2019-2020 - DONOT CHANGE UNLESS TAX RATES CHANGE | E9: Tax Calculations
A10: Single | F10: % of | G10: value of %
A11: If taxable income is over— | B11: but not over— | C11: the tax is: | E11: Given | F11: amt over | G11: of amt over | H11: Total
A12: 0 | B12: 9700 | C12: 10% of the amount over $0 | E12: 0 | F12: 0.1 | G12: =IF(AND($B$2>A12, $B$2<$B12), ($B$2-A12)*$F12, 0) -> 0 | H12: =IF(G12=0, 0,E12+G12) -> 0
A13: 9700 | B13: 39475 | C13: $970 plus 12% of the amount over $9,700 | E13: 970 | F13: 0.12 | G13: =IF(AND($B$2>A13, $B$2<$B13), ($B$2-A13)*$F13, 0) -> 0 | H13: =IF(G13=0, 0,E13+G13) -> 0
A14: 39475 | B14: 84200 | C14: $4,543 plus 22% of the amount over $39,475 | E14: 4543 | F14: 0.22 | G14: =IF(AND($B$2>A14, $B$2<$B14), ($B$2-A14)*$F14, 0) -> 0 | H14: =IF(G14=0, 0,E14+G14) -> 0
A15: 84200 | B15: 160725 | C15: $14,382 plus 24% of the amount over $84,200 | E15: 14382 | F15: 0.24 | G15: =IF(AND($B$2>A15, $B$2<$B15), ($B$2-A15)*$F15, 0) -> 912 | H15: =IF(G15=0, 0,E15+G15) -> 15294
A16: 160725 | B16: 204100 | C16: $32,748 plus 32% of the amount over $160,725 | E16: 32748 | F16: 0.32 | G16: =IF(AND($B$2>A16, $B$2<$B16), ($B$2-A16)*$F16, 0) -> 0 | H16: =IF(G16=0, 0,E16+G16) -> 0
A17: 204100 | B17: 510300 | C17: $46,628 plus 35% of the amount over $204,100 | E17: 46628 | F17: 0.35 | G17: =IF(AND($B$2>A17, $B$2<$B17), ($B$2-A17)*$F17, 0) -> 0 | H17: =IF(G17=0, 0,E17+G17) -> 0
A18: 510300 | B18: no limit | C18: $153,798 plus 37% of the amount over $510,300 | E18: 153798 | F18: 0.37 | G18: =IF(AND($B$2>A18, $B$2<$B18), ($B$2-A18)*$F18, 0) -> 0 | H18: =IF(G18=0, 0,E18+G18) -> 0
A20: Married Filing Jointly | F20: % of | G20: value of %
A21: If taxable income is over— | B21: but not over— | C21: the tax is: | E21: Given | F21: amt over | G21: of amt over | H21: Total
A22: 0 | B22: 19400 | C22: 10% of the amount over $0 | E22: 0 | F22: 0.1 | G22: =IF(AND($B$2>A22, $B$2<$B22), ($B$2-A22)*$F22, 0) -> 0 | H22: =IF(G22=0, 0,E22+G22) -> 0
A23: 19400 | B23: 78950 | C23: $1,940 plus 12% of the amount over $19,400 | E23: 1740 | F23: 0.15 | G23: =IF(AND($B$2>A23, $B$2<$B23), ($B$2-A23)*$F23, 0) -> 0 | H23: =IF(G23=0, 0,E23+G23) -> 0
A24: 78950 | B24: 168400 | C24: $9,086 plus 22% of the amount over $78,950 | E24: 9735 | F24: 0.25 | G24: =IF(AND($B$2>A24, $B$2<$B24), ($B$2-A24)*$F24, 0) -> 2262.5 | H24: =IF(G24=0, 0,E24+G24) -> 11997.5
A25: 168400 | B25: 321450 | C25: $28,765 plus 24% of the amount over $168,400 | E25: 27735 | F25: 0.28 | G25: =IF(AND($B$2>A25, $B$2<$B25), ($B$2-A25)*$F25, 0) -> 0 | H25: =IF(G25=0, 0,E25+G25) -> 0
A26: 321450 | B26: 408200 | C26: $65,497 plus 32% of the amount over $321,450 | E26: 48665 | F26: 0.33 | G26: =IF(AND($B$2>A26, $B$2<$B26), ($B$2-A26)*$F26, 0) -> 0 | H26: =IF(G26=0, 0,E26+G26) -> 0
A27: 408200 | B27: 612350 | C27: $93,257 plus 35% of the amount over $408,200 | E27: 105062 | F27: 0.35 | G27: =IF(AND($B$2>A27, $B$2<$B27), ($B$2-A27)*$F27, 0) -> 0 | H27: =IF(G27=0, 0,E27+G27) -> 0
A28: 612350 | B28: no limit | C28: $164,709 plus 37 % of the amount over $612,350
A30: Source | B30: Current Tax Brackets & Rates
